odoo/addons/stock_move_auto_assign_auto_release_exclude_location/README.rst
odoo/addons/stock_move_auto_assign_auto_release_exclude_location/__init__.py
odoo/addons/stock_move_auto_assign_auto_release_exclude_location/__manifest__.py
odoo/addons/stock_move_auto_assign_auto_release_exclude_location/i18n/it.po
odoo/addons/stock_move_auto_assign_auto_release_exclude_location/i18n/stock_move_auto_assign_auto_release_exclude_location.pot
odoo/addons/stock_move_auto_assign_auto_release_exclude_location/models/__init__.py
odoo/addons/stock_move_auto_assign_auto_release_exclude_location/models/stock_move.py
odoo/addons/stock_move_auto_assign_auto_release_exclude_location/readme/CONTRIBUTORS.rst
odoo/addons/stock_move_auto_assign_auto_release_exclude_location/readme/DESCRIPTION.rst
odoo/addons/stock_move_auto_assign_auto_release_exclude_location/static/description/icon.png
odoo/addons/stock_move_auto_assign_auto_release_exclude_location/static/description/index.html
odoo/addons/stock_move_auto_assign_auto_release_exclude_location/tests/__init__.py
odoo/addons/stock_move_auto_assign_auto_release_exclude_location/tests/test_assign_auto_release_exclude_location.py
odoo_addon_stock_move_auto_assign_auto_release_exclude_location-16.0.1.0.0.4.dist-info/METADATA
odoo_addon_stock_move_auto_assign_auto_release_exclude_location-16.0.1.0.0.4.dist-info/WHEEL
odoo_addon_stock_move_auto_assign_auto_release_exclude_location-16.0.1.0.0.4.dist-info/top_level.txt
odoo_addon_stock_move_auto_assign_auto_release_exclude_location-16.0.1.0.0.4.dist-info/RECORD
