Metadata-Version: 2.1
Name: odoo-addon-stock_move_auto_assign_auto_release_exclude_location
Version: 16.0.1.0.0.4
Summary: Exclude locations from auto release moves after auto assign
Home-page: https://github.com/OCA/stock-logistics-warehouse
Author: BCIM, Camptocamp, Odoo Community Association (OCA)
Author-email: support@odoo-community.org
License: AGPL-3
Classifier: Programming Language :: Python
Classifier: Framework :: Odoo
Classifier: Framework :: Odoo :: 16.0
Classifier: License :: OSI Approved :: GNU Affero General Public License v3
Requires-Python: >=3.10
Requires-Dist: odoo-addon-stock-available-immediately-exclude-location<16.1dev,>=16.0dev
Requires-Dist: odoo-addon-stock-move-auto-assign-auto-release<16.1dev,>=16.0dev
Requires-Dist: odoo<16.1dev,>=16.0a
